{
	"info": {
		"_postman_id": "cb309ad3-47ae-481a-981c-a1648dce8dcc",
		"name": "ExpressAPIs",
		"schema": "https://schema.getpostman.com/json/collection/v2.1.0/collection.json"
	},
	"item": [
		{
			"name": "GETRequest",
			"request": {
				"method": "GET",
				"header": [],
				"url": null
			},
			"response": []
		},
		{
			"name": "POSTRequest",
			"request": {
				"method": "POST",
				"header": [],
				"body": {
					"mode": "raw",
					"raw": "{\r\n    \"test\" : \"data\"\r\n}",
					"options": {
						"raw": {
							"language": "json"
						}
					}
				},
				"url": {
					"raw": "http://localhost:8000/underconstruction?api_key=12",
					"protocol": "http",
					"host": [
						"localhost"
					],
					"port": "8000",
					"path": [
						"underconstruction"
					],
					"query": [
						{
							"key": "api_key",
							"value": "12"
						}
					]
				}
			},
			"response": []
		},
		{
			"name": "CRUDRequest",
			"request": {
				"auth": {
					"type": "noauth"
				},
				"method": "PUT",
				"header": [],
				"body": {
					"mode": "raw",
					"raw": "{\r\n    \"name\": \"name\"\r\n}",
					"options": {
						"raw": {
							"language": "json"
						}
					}
				},
				"url": {
					"raw": "http://localhost:8000/profile",
					"protocol": "http",
					"host": [
						"localhost"
					],
					"port": "8000",
					"path": [
						"profile"
					]
				}
			},
			"response": []
		},
		{
			"name": "Posts",
			"request": {
				"method": "POST",
				"header": [],
				"body": {
					"mode": "raw",
					"raw": "{\r\n        \"name\": \"Test post 2\",\r\n        \"url\": \"https://webapplog.com/es7\",\r\n        \"text\": \"Test post for POST api\",\r\n        \"comments\": [\r\n            {\r\n                \"text\": \"Is this even a comment?????\",\r\n                \"text\": \"Additional dummy comments!!!!\"\r\n            }\r\n        ]\r\n    }",
					"options": {
						"raw": {
							"language": "json"
						}
					}
				},
				"url": {
					"raw": "http://localhost:8000/posts/",
					"protocol": "http",
					"host": [
						"localhost"
					],
					"port": "8000",
					"path": [
						"posts",
						""
					]
				}
			},
			"response": []
		},
		{
			"name": "Comments",
			"request": {
				"method": "GET",
				"header": [],
				"url": null
			},
			"response": []
		}
	]
}